nixtract/__init__.py
nixtract/__main__.py
nixtract/cli.py
nixtract/describe-derivation.nix
nixtract/find-attribute-paths.nix
nixtract/lib.nix
nixtract/model.py
nixtract/threading.py
nixtract_cli-0.1.0.dist-info/LICENSE
nixtract_cli-0.1.0.dist-info/METADATA
nixtract_cli-0.1.0.dist-info/WHEEL
nixtract_cli-0.1.0.dist-info/entry_points.txt
nixtract_cli-0.1.0.dist-info/RECORD
