Metadata-Version: 2.1
Name: nixtract-cli
Version: 0.1.0
Summary: A CLI tool to extract the graph of derivations from a Nix flake.
License: MIT
Author: Guillaume Desforges
Author-email: guillaume.desforges@tweag.io
Requires-Python: >=3.10,<4.0
Classifier: License :: OSI Approved :: MIT License
Classifier: Programming Language :: Python :: 3
Classifier: Programming Language :: Python :: 3.10
Classifier: Programming Language :: Python :: 3.11
Classifier: Programming Language :: Python :: 3.12
Requires-Dist: click (>=8.1.3,<9.0.0)
Requires-Dist: pydantic (>=1.10.7,<2.0.0)
